fcontroller/Core.py
fcontroller/FController.py
fcontroller/FControllerError.py
fcontroller/Module.py
fcontroller/__init__.py
FControllerPY-0.0.1.dist-info/LICENSE
FControllerPY-0.0.1.dist-info/METADATA
FControllerPY-0.0.1.dist-info/WHEEL
FControllerPY-0.0.1.dist-info/top_level.txt
FControllerPY-0.0.1.dist-info/RECORD
