Metadata-Version: 2.1
Name: FControllerPY
Version: 0.0.1
Summary: Container and Front Controller for modules or controllers.
Home-page: https://github.com/othercodes/fcontroller-py
Author: Unay Santisteban
Author-email: usantisteban@othercode.es
Maintainer: Unay Santisteban
License: UNKNOWN
Platform: UNKNOWN
Classifier: Programming Language :: Python :: 3
Classifier: License :: OSI Approved :: MIT License
Classifier: Operating System :: OS Independent
